smartreq/__init__.py
smartreq/cli.py
smartreq-0.1.2.dist-info/licenses/LICENSE
smartreq-0.1.2.dist-info/METADATA
smartreq-0.1.2.dist-info/WHEEL
smartreq-0.1.2.dist-info/entry_points.txt
smartreq-0.1.2.dist-info/top_level.txt
smartreq-0.1.2.dist-info/RECORD
