Metadata-Version: 2.4
Name: smartreq
Version: 0.1.2
Summary: CLI tool to auto-generate requirements.txt with exact versions
Author: Your Name
Classifier: Programming Language :: Python :: 3
Classifier: License :: OSI Approved :: MIT License
Requires-Python: >=3.7
License-File: LICENSE
Dynamic: author
Dynamic: classifier
Dynamic: description-content-type
Dynamic: license-file
Dynamic: requires-python
Dynamic: summary
